numpyradiomics/__init__.py
numpyradiomics/dro.py
numpyradiomics/mod_filters.py
numpyradiomics/mod_firstorder.py
numpyradiomics/mod_glcm.py
numpyradiomics/mod_gldm.py
numpyradiomics/mod_glrlm.py
numpyradiomics/mod_glszm.py
numpyradiomics/mod_ngtdm.py
numpyradiomics/mod_preproc.py
numpyradiomics/mod_shape.py
numpyradiomics/mod_shape_2d.py
numpyradiomics/mod_shape_3d.py
numpyradiomics/mod_ski_shape_3d.py
numpyradiomics/mod_texture.py
numpyradiomics-0.0.4.dist-info/licenses/LICENSE
numpyradiomics-0.0.4.dist-info/METADATA
numpyradiomics-0.0.4.dist-info/WHEEL
numpyradiomics-0.0.4.dist-info/top_level.txt
numpyradiomics-0.0.4.dist-info/RECORD
