Metadata-Version: 2.4
Name: numpyradiomics
Version: 0.0.4
Summary: A light-weight python-native implementation of pyradiomics
Author-email: Steven Sourbron <s.sourbron@sheffield.ac.uk>
License-Expression: Apache-2.0
Project-URL: Homepage, https://miblab.org/
Project-URL: Source Code, https://github.com/openmiblab/numpyradiomics
Keywords: radiomics,medical-imaging,shape-analysis,numpy,scikit-image
Classifier: Programming Language :: Python :: 3
Classifier: Operating System :: OS Independent
Classifier: Topic :: Scientific/Engineering :: Medical Science Apps.
Classifier: Intended Audience :: Science/Research
Requires-Python: >=3.8
License-File: LICENSE
Requires-Dist: numpy>=1.20
Requires-Dist: scipy>=1.7
Requires-Dist: scikit-image>=0.18
Requires-Dist: PyWavelets
Dynamic: license-file
